LICENSE
MANIFEST.in
README.md
setup.py
data/test-report.txt
krakenplot/__init__.py
krakenplot.egg-info/PKG-INFO
krakenplot.egg-info/SOURCES.txt
krakenplot.egg-info/dependency_links.txt
krakenplot.egg-info/not-zip-safe
krakenplot.egg-info/requires.txt
krakenplot.egg-info/top_level.txt