Metadata-Version: 2.1
Name: krakenplot
Version: 0.1.0
Summary: Plot the summary output from Kraken.
Home-page: https://github.com/clintval/krakenplot
Author: clintval
Author-email: valentine.clint@gmail.com
License: MIT
Download-URL: https://github.com/clintval/krakenplot/archive/v0.1.0.tar.gz
Project-URL: Documentation, https://krakenplot.readthedocs.io
Project-URL: Issue-Tracker, https://github.com/clintval/krakenplot/issues
Keywords: kraken tree phylogeny taxonomy classification
Platform: UNKNOWN
Classifier: Development Status :: 2 - Pre-Alpha
Classifier: Intended Audience :: Developers
Classifier: Intended Audience :: Science/Research
Classifier: License :: OSI Approved :: MIT License
Classifier: Topic :: Scientific/Engineering :: Bio-Informatics
Classifier: Programming Language :: Python :: 3.6
Classifier: Programming Language :: Python :: 3.7
